accscout
